agentwire/__init__.py
agentwire/__main__.py
agentwire/cached_status.py
agentwire/cli_safety.py
agentwire/completion.py
agentwire/config.py
agentwire/errors.py
agentwire/history.py
agentwire/init_agentwire.py
agentwire/listen.py
agentwire/locking.py
agentwire/mcp_server.py
agentwire/network.py
agentwire/notifications.py
agentwire/onboarding.py
agentwire/pane_manager.py
agentwire/project_config.py
agentwire/projects.py
agentwire/server.py
agentwire/tasks.py
agentwire/templating.py
agentwire/tts_server.py
agentwire/tunnels.py
agentwire/validation.py
agentwire/voiceclone.py
agentwire/worktree.py
agentwire/agents/__init__.py
agentwire/agents/base.py
agentwire/agents/tmux.py
agentwire/hooks/__init__.py
agentwire/hooks/agentwire-permission.sh
agentwire/hooks/suppress-bg-notifications.sh
agentwire/hooks/damage-control/__init__.py
agentwire/hooks/damage-control/audit_logger.py
agentwire/hooks/damage-control/bash-tool-damage-control.py
agentwire/hooks/damage-control/edit-tool-damage-control.py
agentwire/hooks/damage-control/patterns.yaml
agentwire/hooks/damage-control/write-tool-damage-control.py
agentwire/prompts/__init__.py
agentwire/prompts/init.md
agentwire/roles/__init__.py
agentwire/roles/chatbot.md
agentwire/roles/claude-delegation.md
agentwire/roles/claude-worker.md
agentwire/roles/glm-delegation.md
agentwire/roles/glm-worker.md
agentwire/roles/leader.md
agentwire/roles/task-runner.md
agentwire/roles/worker.md
agentwire/static/agentwire-splash--agentwire.png
agentwire/static/agentwire-splash--full.png
agentwire/static/agentwire-splash--owl.png
agentwire/static/agentwire-splash--telephone.png
agentwire/static/agentwire-splash--tree.png
agentwire/static/favicon.png
agentwire/static/css/desktop.css
agentwire/static/icons/machines/android.jpeg
agentwire/static/icons/machines/automaton.jpeg
agentwire/static/icons/machines/bot.jpeg
agentwire/static/icons/machines/cyborg.jpeg
agentwire/static/icons/machines/droid.jpeg
agentwire/static/icons/machines/drone.jpeg
agentwire_dev-1.0.3.dist-info/METADATA
agentwire_dev-1.0.3.dist-info/WHEEL
agentwire_dev-1.0.3.dist-info/entry_points.txt
agentwire_dev-1.0.3.dist-info/licenses/LICENSE
agentwire_dev-1.0.3.dist-info/RECORD
