Metadata-Version: 2.4
Name: agentwire-dev
Version: 1.0.3
Summary: Multi-session voice web interface for AI coding agents
Project-URL: Homepage, https://www.agentwire.dev/projects/agentwire-dev
Project-URL: Repository, https://github.com/dotdevdotdev/agentwire-dev
Project-URL: Documentation, https://www.agentwire.dev/projects/agentwire-dev
Author-email: dotdev <dev@dotdev.dev>
License-Expression: AGPL-3.0-or-later
License-File: LICENSE
Keywords: agent,ai,claude,stt,tmux,tts,voice
Classifier: Development Status :: 3 - Alpha
Classifier: Environment :: Web Environment
Classifier: Intended Audience :: Developers
Classifier: License :: OSI Approved :: GNU Affero General Public License v3 or later (AGPLv3+)
Classifier: Operating System :: MacOS
Classifier: Operating System :: POSIX :: Linux
Classifier: Programming Language :: Python :: 3
Classifier: Programming Language :: Python :: 3.10
Classifier: Programming Language :: Python :: 3.11
Classifier: Programming Language :: Python :: 3.12
Classifier: Programming Language :: Python :: 3.13
Classifier: Topic :: Software Development :: User Interfaces
Requires-Python: >=3.10
Requires-Dist: aiohttp-jinja2>=1.6
Requires-Dist: aiohttp>=3.9.0
Requires-Dist: jinja2>=3.1.0
Requires-Dist: mcp>=1.2.0
Requires-Dist: python-dotenv>=1.0.0
Requires-Dist: pyyaml>=6.0
Requires-Dist: requests>=2.28.0
Requires-Dist: resend>=2.0.0
Provides-Extra: dev
Requires-Dist: pytest-asyncio>=0.23.0; extra == 'dev'
Requires-Dist: pytest>=7.0; extra == 'dev'
Requires-Dist: ruff>=0.1.0; extra == 'dev'
Provides-Extra: stt
Requires-Dist: fastapi>=0.104.0; extra == 'stt'
Requires-Dist: faster-whisper>=1.0.0; extra == 'stt'
Requires-Dist: python-multipart>=0.0.6; extra == 'stt'
Requires-Dist: uvicorn>=0.24.0; extra == 'stt'
Provides-Extra: tts
Requires-Dist: chatterbox-tts>=0.1.6; extra == 'tts'
Requires-Dist: fastapi>=0.104.0; extra == 'tts'
Requires-Dist: faster-whisper>=1.0.0; extra == 'tts'
Requires-Dist: pydantic>=2.0.0; extra == 'tts'
Requires-Dist: python-multipart>=0.0.6; extra == 'tts'
Requires-Dist: runpod>=1.6.0; extra == 'tts'
Requires-Dist: torch>=2.0.0; extra == 'tts'
Requires-Dist: torchaudio>=2.0.0; extra == 'tts'
Requires-Dist: uvicorn>=0.24.0; extra == 'tts'
